<?xml version="1.0" encoding="utf-8"?>
<data canvas_height="2617" pattern_url="Vintage Background 5.png" frame_url="Frame 24.png">
  <item type="shape" index="0" shape_type="Rectangle" color="1742066 " xpos="9.95" ypos="168.85" width="888.25" height="383.5" rotation="10.008253485264385"/>
  <item type="shape" index="1" shape_type="Rectangle" color="3430 " xpos="-227.65" ypos="418.3" width="902.5" height="33.1" rotation="-7.754665089773381"/>
  <item type="shape" index="2" shape_type="Rectangle" color="88976 " xpos="-112.7" ypos="-324.15" width="721.1" height="721.05" rotation="-7.254349096648714"/>
  <item type="text" index="3" font="Londrina Solid" size="66" color="16237824@@@16237824@@@16237824@@@16237824@@@16237824@@@16237824@@@16237824@@@16237824@@@16237824@@@16237824@@@16237824@@@16237824@@@16237824@@@16237824@@@16237824@@@16237824@@@16237824@@@16237824" xpos="90.75" ypos="67.45" alignment="center" rotation="-5.502653696805203" scalex="0.7793941297558452" scaley="0.7793942484157896" filter="true"><![CDATA[9 Ways To Increase]]></item>
  <item type="text" index="4" font="Lobster Two" size="66" color="16237824@@@16237824@@@16237824@@@16237824@@@16237824@@@16237824@@@16237824@@@16237824@@@16237824@@@16237824@@@16237824@@@16237824@@@16237824@@@16237824@@@16237824@@@16237824@@@16237824@@@16237824" xpos="25.5" ypos="127.2" alignment="center" rotation="-5.753445249248283" scalex="0.9927173772759946" scaley="0.9927006657856758" filter="true"><![CDATA[Your Sales In 2013]]></item>
  <item type="shape" index="5" shape_type="Circle" color="203690 " xpos="7.75" ypos="437.2" width="93.05" height="93.05" rotation="-5.002446699193469"/>
  <item type="shape" index="6" shape_type="Rectangle" color="88976 " xpos="-122.15" ypos="521.35" width="814.8" height="376.1" rotation="10.008237501206683"/>
  <item type="image" index="7" source="uploaded_image/521cef91da694.png" xpos="302.05" ypos="161.1" width="288.65" height="204" rotation="0"/>
  <item type="text" index="8" font="Courier New" size="66" color="16777215" xpos="18.6" ypos="444.7" alignment="center" rotation="-7.254143083397321" scalex="1.0640127638205112" scaley="1.0640279004772482" filter="true"><![CDATA[1]]></item>
  <item type="text" index="9" font="FrnkGothITC Hv BT" size="35" color="16777215@@@16777215@@@16777215@@@16777215@@@16777215@@@16777215@@@16777215@@@16777215@@@16777215@@@16777215@@@16777215" xpos="98.55" ypos="417.45" alignment="center" rotation="-8.00454377859853" scalex="1.7587122313052936" scaley="1.758696887162855" filter="true"><![CDATA[Review 2012]]></item>
  <item type="image" index="10" source="uploaded_image/521cef91da694.png" xpos="13.3" ypos="202.2" width="288.65" height="204" rotation="0"/>
  <item type="text" index="11" font="Comic Sans MS" size="35" color="16777215" xpos="450.6" ypos="426.65" alignment="center" rotation="-10.75921541217717" scalex="4.568595399932429" scaley="4.56853255582893" filter="true"><![CDATA[?]]></item>
  <item type="shape" index="12" shape_type="Circle" color="16316452 " xpos="24.4" ypos="579.95" width="87.7" height="87.7" rotation="0"/>
  <item type="text" index="13" font="Helvetica Neue" size="26" color="16777215@@@16777215@@@16777215@@@16777215@@@16777215@@@16777215@@@16777215@@@16777215@@@16777215@@@16777215@@@16777215@@@16777215@@@16777215@@@16777215@@@16777215@@@16777215@@@16777215@@@16777215@@@16777215@@@16777215@@@16777215@@@16777215@@@16777215@@@16777215@@@16777215@@@16777215@@@16777215@@@16777215@@@16777215@@@16777215@@@16777215@@@16777215@@@16777215@@@16777215@@@16777215@@@16777215@@@16777215@@@16777215@@@16777215@@@16777215@@@16777215@@@16777215@@@16777215@@@16777215@@@16777215@@@16777215@@@16777215@@@16777215@@@16777215@@@16777215@@@16777215@@@16777215@@@16777215@@@16777215@@@16777215@@@16777215@@@16777215@@@16777215@@@16777215@@@16777215@@@16777215@@@16777215@@@16777215@@@16777215@@@16777215@@@16777215@@@16777215@@@16777215@@@16777215@@@16777215@@@16777215@@@16777215@@@16777215" xpos="120.2" ypos="488.6" alignment="center" rotation="-7.505024991204996" scalex="0.8161345564801179" scaley="0.8160549293962304" filter="true"><![CDATA[Leads, opportunities, closed, lost, ratios, activity
What really went on?]]></item>
  <item type="text" index="14" font="FrnkGothITC Hv BT" size="35" color="16574257@@@16574257@@@16574257@@@16574257@@@16574257@@@16574257@@@16574257@@@16574257@@@16574257@@@16574257@@@16574257@@@16574257@@@16574257@@@16574257@@@16574257@@@16574257@@@16574257" xpos="138.8" ypos="588" alignment="center" rotation="10.508787338591583" scalex="1.44208042844075" scaley="1.4420356543264898" filter="true"><![CDATA[Set 2013 Targets ]]></item>
  <item type="image" index="15" source="uploaded_image/521cf270254c7.png" xpos="599.15" ypos="47.45" width="112.8" height="70.85" rotation="144.41414676675717"/>
  <item type="shape" index="16" shape_type="Rectangle" color="16574745 " xpos="4.7" ypos="101.65" width="88.9" height="32.25" rotation="-7.755769043622521"/>
  <item type="text" index="17" font="Comic Sans MS" size="35" color="16777215" xpos="400.65" ypos="489.15" alignment="center" rotation="-18.274407468855774" scalex="3.0102168103335516" scaley="3.009975567331961" filter="true"><![CDATA[?]]></item>
  <item type="text" index="18" font="Comic Sans MS" size="35" color="16777215" xpos="353.45" ypos="507.2" alignment="center" rotation="-12.261901004057387" scalex="2.236866394640632" scaley="2.2367639681726117" filter="true"><![CDATA[?]]></item>
  <item type="text" index="19" font="Courier New" size="66" color="84903" xpos="43.55" ypos="580.25" alignment="center" rotation="9.507572652361949" scalex="1.0577266801069436" scaley="1.057709345718617" filter="true"><![CDATA[2]]></item>
  <item type="text" index="20" font="Helvetica Neue" size="26" color="16574257@@@16574257@@@16574257@@@16574257@@@16574257@@@16574257@@@16574257@@@16574257@@@16574257@@@16574257@@@16574257@@@16574257@@@16574257@@@16574257@@@16574257@@@16574257@@@16574257@@@16574257@@@16574257@@@16574257@@@16574257@@@16574257@@@16574257@@@16574257@@@16574257@@@16574257@@@16574257@@@16574257@@@16574257@@@16574257@@@16574257@@@16574257@@@16574257@@@16574257@@@16574257@@@16574257@@@16574257@@@16574257@@@16574257@@@16574257@@@16574257@@@16574257" xpos="143.8" ypos="653.85" alignment="center" rotation="11.009747680549465" scalex="0.8104953476119661" scaley="0.8103397985293129" filter="true"><![CDATA[Set targets based on 2012 - not guesswork!]]></item>
  <item type="shape" index="21" shape_type="Rectangle" color="88976 " xpos="-150.45" ypos="1016.9" width="811.85" height="414.8" rotation="0.2500297056185593"/>
  <item type="shape" index="22" shape_type="Rectangle" color="1742066 " xpos="-76.9" ypos="819.7" width="875.2" height="274.25" rotation="-3.500828478231895"/>
  <item type="shape" index="23" shape_type="Circle" color="203690 " xpos="28.85" ypos="873.85" width="92.9" height="92.9" rotation="-5.001511685806866"/>
  <item type="text" index="24" font="Courier New" size="66" color="16777215" xpos="46.05" ypos="878.3" alignment="center" rotation="-3.766362181712686" scalex="1.060410997782366" scaley="1.0603420633237306" filter="true"><![CDATA[3]]></item>
  <item type="text" index="25" font="FrnkGothITC Hv BT" size="35" color="16777215@@@16777215@@@16777215@@@16777215@@@16777215@@@16777215@@@16777215" xpos="129.1" ypos="854.95" alignment="center" rotation="-3.251229345012943" scalex="2.185738267024538" scaley="2.1857689722511013" filter="true"><![CDATA[Revisit]]></item>
  <item type="text" index="26" font="Helvetica Neue" size="26" color="16777215@@@16777215@@@16777215@@@16777215@@@16777215@@@16777215@@@16777215@@@16777215@@@16777215@@@16777215@@@16777215@@@16777215@@@16777215@@@16777215@@@16777215@@@16777215@@@16777215@@@16777215@@@16777215@@@16777215@@@16777215@@@16777215@@@16777215@@@16777215@@@16777215@@@16777215@@@16777215@@@16777215@@@16777215@@@16777215@@@16777215@@@16777215@@@16777215@@@16777215@@@16777215@@@16777215@@@16777215@@@16777215@@@16777215@@@16777215@@@16777215@@@16777215@@@16777215@@@16777215@@@16777215@@@16777215@@@16777215@@@16777215@@@16777215@@@16777215@@@16777215@@@16777215@@@16777215@@@16777215@@@16777215@@@16777215@@@16777215@@@16777215@@@16777215@@@16777215@@@16777215@@@16777215@@@16777215@@@16777215@@@16777215@@@16777215@@@16777215@@@16777215@@@16777215@@@16777215@@@16777215@@@16777215@@@16777215@@@16777215@@@16777215@@@16777215@@@16777215@@@16777215@@@16777215@@@16777215@@@16777215@@@16777215@@@16777215" xpos="33.55" ypos="1004.15" alignment="center" rotation="-3.5012537131444286" scalex="0.9536996122886879" scaley="0.9536509110518359" filter="true"><![CDATA[The wants of your prospects. Have they changed?
How is the world according to them?]]></item>
  <item type="image" index="27" source="uploaded_image/521d7994530dc.png" xpos="433.95" ypos="798.2" width="142.3" height="164.5" rotation="-4.211780648058446"/>
  <item type="text" index="28" font="Londrina Solid" size="26" color="16461@@@16461@@@16461@@@16461" xpos="419.7" ypos="886.95" alignment="center" rotation="-4.29971081706352" scalex="1.3598022983884999" scaley="1.3597446261483006" filter="true"><![CDATA[WANT]]></item>
  <item type="text" index="29" font="Londrina Solid" size="26" color="16461@@@16461@@@16461@@@16461" xpos="518.65" ypos="880.25" alignment="center" rotation="-5.25164827016618" scalex="1.3514982673162093" scaley="1.3514528025020354" filter="true"><![CDATA[NEED]]></item>
  <item type="shape" index="30" shape_type="Circle" color="16316452 " xpos="16.35" ypos="1101.65" width="87.7" height="87.7" rotation="-2.001888626281315"/>
  <item type="text" index="31" font="Courier New" size="66" color="84903" xpos="26.05" ypos="1107.45" alignment="center" rotation="-4.004189964991293" scalex="1.0525876141294557" scaley="1.0525572899668085" filter="true"><![CDATA[4]]></item>
  <item type="text" index="32" font="FrnkGothITC Hv BT" size="35" color="16574257@@@16574257@@@16574257@@@16574257@@@16574257@@@16574257@@@16574257@@@16574257@@@16574257@@@16574257@@@16574257@@@16574257@@@16574257@@@16574257@@@16574257@@@16574257@@@16574257@@@16574257@@@16574257@@@16574257@@@16574257@@@16574257" xpos="116.6" ypos="1103.6" alignment="center" rotation="-3.2511094474990667" scalex="1.1620568945768135" scaley="1.162310575350286" filter="true"><![CDATA[Increase Lead
Sources]]></item>
  <item type="text" index="33" font="Helvetica Neue" size="26" color="16574257@@@16574257@@@16574257@@@16574257@@@16574257@@@16574257@@@16574257@@@16574257@@@16574257@@@16574257@@@16574257@@@16574257@@@16574257@@@16574257@@@16574257@@@16574257@@@16574257@@@16574257@@@16574257@@@16574257@@@16574257@@@16574257@@@16574257@@@16574257@@@16574257@@@16574257@@@16574257@@@16574257@@@16574257@@@16574257@@@16574257@@@16574257@@@16574257@@@16574257@@@16574257@@@16574257@@@16574257@@@16574257@@@16574257@@@16574257@@@16574257@@@16574257@@@16574257@@@16574257@@@16574257@@@16574257@@@16574257@@@16574257@@@16574257@@@16574257@@@16574257" xpos="3.6" ypos="1212.2" alignment="center" rotation="-3.251560001072991" scalex="0.9512536283435665" scaley="0.9512863484893033" filter="true"><![CDATA[How many lead sources do you have?
Increase them...]]></item>
  <item type="text" index="34" font="Helvetica Neue" size="26" color="16574257@@@16574257@@@16574257@@@16574257@@@16574257@@@16574257@@@16574257@@@16574257@@@16574257@@@16574257@@@16574257@@@16574257@@@16574257@@@16574257@@@16574257@@@16574257@@@16574257@@@16574257@@@16574257@@@16574257@@@16574257@@@16574257@@@16574257@@@16574257@@@16574257@@@16574257@@@16574257@@@16574257@@@16574257@@@16574257@@@16574257@@@16574257@@@16574257@@@16574257@@@16574257@@@16574257@@@16574257@@@16574257@@@16574257@@@16574257@@@16574257@@@16574257@@@16574257@@@16574257@@@16574257@@@16574257@@@16574257@@@16574257@@@16574257@@@16574257@@@16574257@@@16574257@@@16574257@@@16574257@@@16574257@@@16574257@@@16574257@@@16574257@@@16574257@@@16574257@@@16574257@@@16574257@@@16574257@@@16574257@@@16574257@@@16574257@@@16574257@@@16574257@@@16574257@@@16574257@@@16574257@@@16574257@@@16574257@@@16574257@@@16574257@@@16574257@@@16574257@@@16574257@@@16574257" xpos="9.7" ypos="1278.3" alignment="center" rotation="-3.2513036679524165" scalex="0.6798662988094984" scaley="0.6798662988094984" filter="true"><![CDATA[Cold Calling | Social Media | Channel Sites | Referrals | Internet | Networking]]></item>
  <item type="shape" index="35" shape_type="Rectangle" color="88976 " xpos="-147.7" ypos="1553.3" width="811.65" height="605.85" rotation="0.2500287683116189"/>
  <item type="image" index="36" source="uploaded_image/521d7f34d699d.png" xpos="429.25" ypos="1076.35" width="142.65" height="173.5" rotation="-3.271118378747432"/>
  <item type="image" index="37" source="uploaded_image/521d93328a57a.png" xpos="33.55" ypos="662.25" width="118.6" height="127.15" rotation="0"/>
  <item type="shape" index="38" shape_type="Rectangle" color="1742066 " xpos="-53.55" ypos="1330.8" width="874.65" height="274.1" rotation="-3.5008293748681965"/>
  <item type="shape" index="39" shape_type="Circle" color="203690 " xpos="13.3" ypos="1347.75" width="92.8" height="92.8" rotation="-5.00151283089201"/>
  <item type="text" index="40" font="Courier New" size="66" color="16777215" xpos="29.4" ypos="1352.75" alignment="center" rotation="-3.751756521741897" scalex="1.0582370080729468" scaley="1.0581827004583684" filter="true"><![CDATA[5]]></item>
  <item type="text" index="41" font="FrnkGothITC Hv BT" size="35" color="16777215@@@16777215@@@16777215@@@16777215@@@16777215@@@16777215@@@16777215@@@16777215@@@16777215@@@16777215@@@16777215@@@16777215@@@16777215@@@16777215@@@16777215@@@16777215@@@16777215@@@16777215@@@16777215@@@16777215@@@16777215@@@16777215@@@16777215@@@16777215@@@16777215@@@16777215@@@16777215@@@16777215@@@16777215@@@16777215@@@16777215" xpos="113.55" ypos="1336.35" alignment="center" rotation="-3.251075757618219" scalex="1.1973157467898703" scaley="1.1973157467898703" filter="true"><![CDATA[Building The
Value Proposition]]></item>
  <item type="text" index="42" font="Helvetica Neue" size="26" color="16777215@@@16777215@@@16777215@@@16777215@@@16777215@@@16777215@@@16777215@@@16777215@@@16777215@@@16777215@@@16777215@@@16777215@@@16777215@@@16777215@@@16777215@@@16777215@@@16777215@@@16777215@@@16777215@@@16777215@@@16777215@@@16777215@@@16777215@@@16777215@@@16777215@@@16777215@@@16777215@@@16777215@@@16777215@@@16777215@@@16777215@@@16777215@@@16777215@@@16777215@@@16777215@@@16777215@@@16777215@@@16777215@@@16777215@@@16777215@@@16777215@@@16777215@@@16777215@@@16777215@@@16777215@@@16777215@@@16777215@@@16777215@@@16777215@@@16777215@@@16777215@@@16777215@@@16777215@@@16777215@@@16777215@@@16777215@@@16777215@@@16777215@@@16777215@@@16777215@@@16777215@@@16777215@@@16777215@@@16777215@@@16777215@@@16777215@@@16777215@@@16777215@@@16777215@@@16777215@@@16777215@@@16777215@@@16777215@@@16777215@@@16777215@@@16777215@@@16777215@@@16777215@@@16777215@@@16777215@@@16777215@@@16777215@@@16777215@@@16777215@@@16777215@@@16777215@@@16777215@@@16777215" xpos="4.15" ypos="1468.3" alignment="center" rotation="-3.5004729457171653" scalex="0.8964325514040777" scaley="0.8968029344108802" filter="true"><![CDATA[What would make the sale
a complete "no-brainer?"
Revisit USPs. Are they really unique?]]></item>
  <item type="image" index="43" source="uploaded_image/521d95fb8aca5.png" xpos="374" ypos="1437.2" width="216.65" height="122.35" rotation="-4.27026712331736"/>
  <item type="shape" index="44" shape_type="Circle" color="16316452 " xpos="64.1" ypos="1622.75" width="87.65" height="87.65" rotation="-1.9998848612733888"/>
  <item type="text" index="45" font="Courier New" size="66" color="84903" xpos="71.6" ypos="1629.15" alignment="center" rotation="-4.001270277370269" scalex="1.051605031654909" scaley="1.0515745884654306" filter="true"><![CDATA[6]]></item>
  <item type="text" index="46" font="FrnkGothITC Hv BT" size="35" color="16574257@@@16574257@@@16574257@@@16574257@@@16574257@@@16574257@@@16574257@@@16574257@@@16574257@@@16574257@@@16574257@@@16574257@@@16574257@@@16574257@@@16574257@@@16574257@@@16574257@@@16574257@@@16574257@@@16574257@@@16574257@@@16574257@@@16574257@@@16574257@@@16574257@@@16574257@@@16574257@@@16574257@@@16574257@@@16574257@@@16574257" xpos="169.05" ypos="1608.6" alignment="center" rotation="-3.2508342469293963" scalex="1.1952519646972357" scaley="1.1953314717942232" filter="true"><![CDATA[Cultivate Existing
Client Base]]></item>
  <item type="text" index="47" font="Helvetica Neue" size="26" color="16574257@@@16574257@@@16574257@@@16574257@@@16574257@@@16574257@@@16574257@@@16574257@@@16574257@@@16574257@@@16574257@@@16574257@@@16574257@@@16574257@@@16574257@@@16574257@@@16574257@@@16574257@@@16574257@@@16574257@@@16574257@@@16574257@@@16574257@@@16574257@@@16574257@@@16574257@@@16574257@@@16574257@@@16574257@@@16574257@@@16574257@@@16574257@@@16574257@@@16574257@@@16574257@@@16574257" xpos="9.7" ypos="1750.55" alignment="center" rotation="-3.500425852282712" scalex="0.8944451560442401" scaley="0.8949470630059736" filter="true"><![CDATA[Up-Sell | Cross-Sell | Vertical-Sell]]></item>
  <item type="text" index="48" font="FrnkGothITC Hv BT" size="35" color="16777215@@@16777215@@@16777215@@@16777215" xpos="471.45" ypos="1696.35" alignment="center" rotation="-3.250834570979725" scalex="1.1952518456797725" scaley="1.1952512185267674" filter="true"><![CDATA[SELL]]></item>
  <item type="text" index="49" font="Letter Gothic Std" size="35" color="16777215@@@16777215@@@16777215@@@16777215" xpos="475.3" ypos="1738.3" alignment="center" rotation="-3.2513475213049756" scalex="1.1947943100133327" scaley="1.194794310435902" filter="true"><![CDATA[SELL]]></item>
  <item type="shape" index="50" shape_type="Rectangle" color="88976 " xpos="-168.5" ypos="1999.95" width="811.25" height="319.3" rotation="0.2500519765532272"/>
  <item type="text" index="51" font="Helvetica Neue" size="35" color="16777215@@@16777215@@@16777215@@@16777215" xpos="361.2" ypos="1704.7" alignment="center" rotation="-3.251132694324684" scalex="1.194335195722334" scaley="1.194335433334649" filter="true"><![CDATA[SELL]]></item>
  <item type="text" index="52" font="Hand Of Sean" size="35" color="16777215@@@16777215@@@16777215@@@16777215" xpos="363.45" ypos="1744.95" alignment="center" rotation="-3.2510695163457926" scalex="0.8604546294682442" scaley="0.8605122769214425" filter="true"><![CDATA[SELL]]></item>
  <item type="shape" index="53" shape_type="Rectangle" color="1742066 " xpos="-124.65" ypos="1805.55" width="872.05" height="271.1" rotation="2.2503706846363087"/>
  <item type="shape" index="54" shape_type="Circle" color="203690 " xpos="8.85" ypos="1828.85" width="92.7" height="92.7" rotation="-5.001660288115729"/>
  <item type="text" index="55" font="Courier New" size="66" color="16777215" xpos="29.4" ypos="1831.35" alignment="center" rotation="3.7514985788660957" scalex="1.0548115066856656" scaley="1.0548338243300466" filter="true"><![CDATA[7]]></item>
  <item type="text" index="56" font="FrnkGothITC Hv BT" size="35" color="16777215@@@16777215@@@16777215@@@16777215@@@16777215@@@16777215@@@16777215@@@16777215@@@16777215@@@16777215@@@16777215@@@16777215@@@16777215@@@16777215@@@16777215@@@16777215@@@16777215@@@16777215@@@16777215@@@16777215@@@16777215" xpos="101.6" ypos="1826.1" alignment="center" rotation="2.50966000182188" scalex="1.1917711352229736" scaley="1.1920502567569804" filter="true"><![CDATA[Shop The
Competition]]></item>
  <item type="text" index="57" font="Helvetica Neue" size="26" color="16777215@@@16777215@@@16777215@@@16777215@@@16777215@@@16777215@@@16777215@@@16777215@@@16777215@@@16777215@@@16777215@@@16777215@@@16777215@@@16777215@@@16777215@@@16777215@@@16777215@@@16777215@@@16777215@@@16777215@@@16777215@@@16777215@@@16777215@@@16777215@@@16777215@@@16777215@@@16777215@@@16777215@@@16777215@@@16777215@@@16777215@@@16777215@@@16777215@@@16777215@@@16777215@@@16777215@@@16777215@@@16777215@@@16777215@@@16777215@@@16777215@@@16777215@@@16777215@@@16777215@@@16777215@@@16777215@@@16777215@@@16777215@@@16777215@@@16777215@@@16777215@@@16777215@@@16777215@@@16777215@@@16777215@@@16777215@@@16777215@@@16777215@@@16777215@@@16777215@@@16777215@@@16777215@@@16777215@@@16777215@@@16777215@@@16777215@@@16777215@@@16777215@@@16777215@@@16777215@@@16777215@@@16777215@@@16777215@@@16777215@@@16777215@@@16777215@@@16777215@@@16777215@@@16777215@@@16777215@@@16777215@@@16777215@@@16777215@@@16777215@@@16777215@@@16777215@@@16777215@@@16777215@@@16777215@@@16777215@@@16777215@@@16777215@@@16777215@@@16777215@@@16777215@@@16777215@@@16777215@@@16777215@@@16777215@@@16777215@@@16777215@@@16777215@@@16777215@@@16777215@@@16777215@@@16777215@@@16777215@@@16777215@@@16777215@@@16777215@@@16777215@@@16777215@@@16777215@@@16777215@@@16777215@@@16777215@@@16777215@@@16777215@@@16777215@@@16777215@@@16777215@@@16777215@@@16777215@@@16777215@@@16777215@@@16777215@@@16777215@@@16777215@@@16777215@@@16777215@@@16777215@@@16777215@@@16777215@@@16777215@@@16777215@@@16777215@@@16777215@@@16777215@@@16777215@@@16777215@@@16777215@@@16777215" xpos="22.45" ypos="1935.8" alignment="center" rotation="2.751243477186753" scalex="0.8923248698446509" scaley="0.8929095066550152" filter="true"><![CDATA[What was a competitive advantage
six months ago, may not be today.
Reassess your competitor's strengths
and weaknesses as well as your own.]]></item>
  <item type="image" index="58" source="uploaded_image/521d99340e616.png" xpos="405.35" ypos="1840.25" width="194.9" height="232.55" rotation="2.251412577208819"/>
  <item type="text" index="59" font="Helvetica Neue" size="26" color="1742066@@@1742066@@@1742066@@@1742066@@@1742066@@@1742066@@@1742066@@@1742066" xpos="420.9" ypos="1869.15" alignment="center" rotation="5.540606089486866" scalex="0.8894398677183045" scaley="0.8900977007910391" filter="true"><![CDATA[STRENGTH]]></item>
  <item type="text" index="60" font="Helvetica Neue" size="26" color="1742066@@@1742066@@@1742066@@@1742066@@@1742066@@@1742066@@@1742066@@@1742066" xpos="448.4" ypos="1946.9" alignment="center" rotation="0.8120289956824251" scalex="0.8861057174930582" scaley="0.8867468148242236" filter="true"><![CDATA[WEAKNESS]]></item>
  <item type="shape" index="61" shape_type="Circle" color="16316452 " xpos="27.45" ypos="2118.3" width="87.65" height="87.65" rotation="-1.8128751374128314"/>
  <item type="text" index="62" font="Courier New" size="66" color="84903" xpos="36.05" ypos="2124.7" alignment="center" rotation="-4.001225166067581" scalex="1.0503048075900334" scaley="1.0502743643988812" filter="true"><![CDATA[8]]></item>
  <item type="text" index="63" font="FrnkGothITC Hv BT" size="35" color="16574257@@@16574257@@@16574257@@@16574257@@@16574257@@@16574257@@@16574257@@@16574257@@@16574257@@@16574257@@@16574257@@@16574257@@@16574257@@@16574257@@@16574257@@@16574257@@@16574257@@@16574257@@@16574257" xpos="134.9" ypos="2104.95" alignment="center" rotation="2.5010065710643707" scalex="1.190297019335455" scaley="1.190707045573774" filter="true"><![CDATA[Mindset &
Attitude]]></item>
  <item type="text" index="64" font="Helvetica Neue" size="26" color="16574257@@@16574257@@@16574257@@@16574257@@@16574257@@@16574257@@@16574257@@@16574257@@@16574257@@@16574257@@@16574257@@@16574257@@@16574257@@@16574257@@@16574257@@@16574257@@@16574257@@@16574257@@@16574257@@@16574257@@@16574257@@@16574257@@@16574257@@@16574257@@@16574257@@@16574257@@@16574257@@@16574257@@@16574257@@@16574257@@@16574257@@@16574257" xpos="35.8" ypos="2213.6" alignment="center" rotation="2.750658498651805" scalex="0.8915606125872185" scaley="0.8921405106805246" filter="true"><![CDATA[List your achievements from 2012]]></item>
  <item type="image" index="65" source="uploaded_image/521d9d7bd7470.png" xpos="408.15" ypos="2111.65" width="138.55" height="157.2" rotation="4.251833918095582"/>
  <item type="shape" index="66" shape_type="Rectangle" color="1742066 " xpos="-105.2" ypos="2308.85" width="868.25" height="397.6" rotation="-1.253002019785208"/>
  <item type="shape" index="67" shape_type="Circle" color="203690 " xpos="13.3" ypos="2341.1" width="92.6" height="92.6" rotation="-5.001438277025373"/>
  <item type="text" index="68" font="Courier New" size="66" color="16777215" xpos="28" ypos="2341.65" alignment="center" rotation="0.5130680070043362" scalex="1.053081653081158" scaley="1.0531422819154337" filter="true"><![CDATA[9]]></item>
  <item type="text" index="69" font="FrnkGothITC Hv BT" size="35" color="16777215@@@16777215@@@16777215@@@16777215@@@16777215@@@16777215@@@16777215@@@16777215@@@16777215@@@16777215@@@16777215@@@16777215@@@16777215@@@16777215@@@16777215@@@16777215@@@16777215@@@16777215@@@16777215@@@16777215@@@16777215@@@16777215@@@16777215@@@16777215@@@16777215@@@16777215@@@16777215@@@16777215@@@16777215" xpos="107.4" ypos="2333" alignment="center" rotation="0.31241372820436586" scalex="1.189333476112778" scaley="1.1898764224479033" filter="true"><![CDATA[Eliminate The
Ghosts Of 2012]]></item>
  <item type="text" index="70" font="Helvetica Neue" size="26" color="16777215@@@16777215@@@16777215@@@16777215@@@16777215@@@16777215@@@16777215@@@16777215@@@16777215@@@16777215@@@16777215@@@16777215@@@16777215@@@16777215@@@16777215@@@16777215@@@16777215@@@16777215@@@16777215@@@16777215@@@16777215@@@16777215@@@16777215@@@16777215@@@16777215@@@16777215@@@16777215@@@16777215@@@16777215@@@16777215@@@16777215@@@16777215@@@16777215@@@16777215@@@16777215@@@16777215@@@16777215@@@16777215@@@16777215@@@16777215@@@16777215@@@16777215@@@16777215@@@16777215@@@16777215@@@16777215@@@16777215@@@16777215@@@16777215@@@16777215@@@16777215@@@16777215@@@16777215@@@16777215@@@16777215@@@16777215@@@16777215@@@16777215@@@16777215@@@16777215@@@16777215@@@16777215@@@16777215@@@16777215@@@16777215@@@16777215@@@16777215@@@16777215@@@16777215@@@16777215@@@16777215@@@16777215@@@16777215@@@16777215@@@16777215@@@16777215@@@16777215@@@16777215@@@16777215@@@16777215@@@16777215@@@16777215@@@16777215@@@16777215@@@16777215@@@16777215@@@16777215@@@16777215@@@16777215@@@16777215@@@16777215@@@16777215@@@16777215@@@16777215@@@16777215@@@16777215@@@16777215@@@16777215@@@16777215@@@16777215@@@16777215@@@16777215@@@16777215@@@16777215@@@16777215@@@16777215@@@16777215@@@16777215@@@16777215@@@16777215@@@16777215@@@16777215@@@16777215@@@16777215@@@16777215@@@16777215@@@16777215@@@16777215@@@16777215@@@16777215@@@16777215@@@16777215@@@16777215@@@16777215@@@16777215@@@16777215@@@16777215@@@16777215@@@16777215@@@16777215" xpos="16.05" ypos="2443.85" alignment="center" rotation="0.2502668782631148" scalex="0.890801284975444" scaley="0.8913812922462881" filter="true"><![CDATA[What's done is done - forget about it.
What's your mindset going to go before,
during and after the sale going into the new year?]]></item>
  <item type="image" index="71" source="uploaded_image/521d9eb2b61d0.png" xpos="468.95" ypos="2319.65" width="132" height="134.7" rotation="5.505477857978346"/>
</data>