<?xml version="1.0" encoding="utf-8"?>
<data canvas_height="2617" pattern_url="Vintage Background 8.png" frame_url="Frame 23.png">
  <item type="image" index="0" source="assets/graphics/Icons/186.png" xpos="4.25" ypos="508.75" width="75.95" height="75.95" rotation="-12.262051209291776"/>
  <item type="text" index="1" font="FrnkGothITC Hv BT" size="66" color="15097145@@@15097145@@@15097145@@@15097145" xpos="30" ypos="35.75" alignment="center" rotation="0" scalex="1.8966522216796875" scaley="1.8966522216796875" filter="true"><![CDATA[FAST]]></item>
  <item type="text" index="2" font="FrnkGothITC Hv BT" size="26" color="5984583@@@5984583@@@5984583@@@5984583" xpos="343" ypos="54" alignment="center" rotation="0" scalex="2.3741607666015625" scaley="2.3741607666015625" filter="true"><![CDATA[FOOD]]></item>
  <item type="image" index="3" source="assets/graphics/Icons/185.png" xpos="487.25" ypos="90.25" width="90.45" height="90.45" rotation="-3.0039783116841914"/>
  <item type="text" index="4" font="FrnkGothITC Hv BT" size="25" color="7755651@@@7755651@@@7755651@@@7755651@@@7755651" xpos="345" ypos="105" alignment="center" rotation="0" scalex="2.21044921875" scaley="2.21044921875" filter="true"><![CDATA[FACTS]]></item>
  <item type="text" index="5" font="Helvetica Neue" size="28" color="5984583@@@5984583@@@5984583@@@5984583@@@5984583@@@5984583@@@5984583@@@5984583@@@5984583@@@5984583@@@5984583@@@5984583@@@5984583@@@5984583@@@5984583@@@5984583@@@5984583@@@5984583@@@5984583@@@5984583@@@5984583@@@5984583@@@5984583@@@5984583@@@5984583@@@5984583@@@5984583@@@5984583@@@5984583@@@5984583@@@5984583@@@5984583@@@5984583@@@5984583@@@5984583@@@5984583@@@5984583@@@5984583@@@5984583@@@5984583@@@5984583@@@5984583@@@5984583@@@5984583@@@5984583@@@5984583@@@5984583@@@5984583@@@5984583@@@5984583@@@5984583@@@5984583@@@5984583@@@5984583@@@5984583@@@5984583@@@5984583@@@5984583@@@5984583@@@5984583@@@5984583@@@5984583@@@5984583@@@5984583@@@5984583@@@5984583@@@5984583@@@5984583@@@5984583@@@5984583@@@5984583@@@5984583@@@5984583@@@5984583@@@5984583@@@5984583@@@5984583@@@5984583@@@5984583@@@5984583@@@5984583@@@5984583@@@5984583@@@5984583@@@5984583@@@5984583@@@5984583@@@5984583@@@5984583@@@5984583@@@5984583@@@5984583" xpos="139.75" ypos="259.25" alignment="left" rotation="0" scalex="0.5839385986328125" scaley="0.5839385986328125" filter="true"><![CDATA[Every month, approximately
nine out of 10 American children visit
a McDonald's restaurant.]]></item>
  <item type="image" index="6" source="assets/graphics/Icons/62.png" xpos="22.25" ypos="117.5" width="64" height="64" rotation="0.5002190794274899"/>
  <item type="image" index="7" source="assets/graphics/People/7.png" xpos="95" ypos="255" width="14" height="30.9" rotation="0"/>
  <item type="image" index="8" source="assets/graphics/People/8.png" xpos="112.75" ypos="292.75" width="13.6" height="32.75" rotation="-0.5006217552347547"/>
  <item type="image" index="9" source="assets/graphics/People/7.png" xpos="42" ypos="255" width="14" height="30.9" rotation="0"/>
  <item type="image" index="10" source="assets/graphics/People/7.png" xpos="59" ypos="255" width="14" height="30.9" rotation="0"/>
  <item type="image" index="11" source="assets/graphics/People/7.png" xpos="76" ypos="255" width="14" height="30.9" rotation="0"/>
  <item type="image" index="12" source="assets/graphics/People/8.png" xpos="41.75" ypos="292.75" width="13.6" height="32.75" rotation="-0.5005229257034253"/>
  <item type="image" index="13" source="assets/graphics/People/8.png" xpos="58.75" ypos="292.75" width="13.6" height="32.75" rotation="-0.5005476294279905"/>
  <item type="image" index="14" source="assets/graphics/People/8.png" xpos="76.75" ypos="292.75" width="13.6" height="32.75" rotation="-0.5006711846370997"/>
  <item type="image" index="15" source="assets/graphics/People/8.png" xpos="94.75" ypos="292.75" width="13.6" height="32.75" rotation="-0.5005970441932941"/>
  <item type="image" index="16" source="assets/graphics/People/3.png" xpos="112.5" ypos="254" width="14.9" height="32.9" rotation="0"/>
  <item type="text" index="17" font="Helvetica Neue" size="28" color="5984583@@@5984583@@@5984583@@@5984583@@@5984583@@@5984583@@@5984583@@@5984583@@@5984583@@@5984583@@@5984583@@@5984583@@@5984583@@@5984583@@@5984583@@@5984583@@@5984583@@@5984583@@@5984583@@@5984583@@@5984583@@@5984583@@@5984583@@@5984583@@@5984583@@@5984583@@@5984583@@@5984583@@@5984583@@@5984583@@@5984583@@@5984583@@@5984583@@@5984583@@@5984583@@@5984583@@@5984583@@@5984583@@@5984583@@@5984583@@@5984583@@@5984583@@@5984583@@@5984583@@@5984583@@@5984583@@@5984583@@@5984583@@@5984583@@@5984583@@@5984583@@@5984583@@@5984583@@@5984583@@@5984583@@@5984583@@@5984583@@@5984583@@@5984583@@@5984583@@@5984583@@@5984583@@@5984583@@@5984583@@@5984583@@@5984583@@@5984583@@@5984583@@@5984583@@@5984583@@@5984583@@@5984583@@@5984583@@@5984583@@@5984583@@@5984583@@@5984583@@@5984583@@@5984583@@@5984583@@@5984583@@@5984583@@@5984583@@@5984583@@@5984583@@@5984583@@@5984583@@@5984583@@@5984583@@@5984583@@@5984583@@@5984583@@@5984583@@@5984583@@@5984583@@@5984583@@@5984583@@@5984583@@@5984583@@@5984583@@@5984583@@@5984583@@@5984583@@@5984583@@@5984583@@@5984583@@@5984583" xpos="171.5" ypos="392" alignment="right" rotation="0" scalex="0.56719970703125" scaley="0.56719970703125" filter="true"><![CDATA[In 1970, Americans spent about $6 billion
on fast food. In 2006, the spending rose
to nearly $142 billion]]></item>
  <item type="image" index="18" source="assets/graphics/Indicators/Indicator 12.png" xpos="328.25" ypos="388.15" width="77" height="79" rotation="-88.6227894857333"/>
  <item type="image" index="19" source="assets/graphics/Icons/139.png" xpos="466" ypos="375.75" width="64" height="64" rotation="0"/>
  <item type="image" index="20" source="assets/graphics/Icons/136.png" xpos="506.75" ypos="409" width="50" height="50" rotation="-0.50366158737806"/>
  <item type="image" index="21" source="assets/graphics/Icons/137.png" xpos="462" ypos="415.75" width="64" height="64" rotation="0"/>
  <item type="image" index="22" source="assets/graphics/Icons/186.png" xpos="52.75" ypos="533.25" width="62.95" height="62.95" rotation="11.510493804818696"/>
  <item type="text" index="23" font="Helvetica Neue" size="28" color="5984583@@@5984583@@@5984583@@@5984583@@@5984583@@@5984583@@@5984583@@@5984583@@@5984583@@@5984583@@@5984583@@@5984583@@@5984583@@@5984583@@@5984583@@@5984583@@@5984583@@@5984583@@@5984583@@@5984583@@@5984583@@@5984583@@@5984583@@@5984583@@@5984583@@@5984583@@@5984583@@@5984583@@@5984583@@@5984583@@@5984583@@@5984583@@@5984583@@@5984583@@@5984583@@@5984583@@@5984583@@@5984583@@@5984583@@@5984583@@@5984583@@@5984583@@@5984583@@@5984583@@@5984583@@@5984583@@@5984583@@@5984583@@@5984583@@@5984583@@@5984583@@@5984583@@@5984583@@@5984583@@@5984583@@@5984583@@@5984583@@@5984583@@@5984583@@@5984583@@@5984583@@@5984583@@@5984583@@@5984583@@@5984583@@@5984583@@@5984583@@@5984583@@@5984583@@@5984583@@@5984583@@@5984583@@@5984583@@@5984583@@@5984583@@@5984583@@@5984583@@@5984583@@@5984583@@@5984583@@@5984583@@@5984583@@@5984583@@@5984583@@@5984583@@@5984583@@@5984583@@@5984583@@@5984583@@@5984583@@@5984583@@@5984583@@@5984583@@@5984583@@@5984583@@@5984583@@@5984583@@@5984583@@@5984583@@@5984583@@@5984583@@@5984583@@@5984583@@@5984583@@@5984583@@@5984583@@@5984583@@@5984583@@@5984583@@@5984583@@@5984583@@@5984583@@@5984583@@@5984583@@@5984583@@@5984583@@@5984583@@@5984583@@@5984583@@@5984583@@@5984583@@@5984583@@@5984583@@@5984583@@@5984583@@@5984583@@@5984583@@@5984583@@@5984583@@@5984583@@@5984583@@@5984583@@@5984583@@@5984583@@@5984583@@@5984583@@@5984583@@@5984583@@@5984583@@@5984583@@@5984583@@@5984583@@@5984583@@@5984583@@@5984583@@@5984583@@@5984583@@@5984583@@@5984583@@@5984583@@@5984583@@@5984583@@@5984583@@@5984583@@@5984583@@@5984583@@@5984583@@@5984583@@@5984583@@@5984583@@@5984583@@@5984583@@@5984583@@@5984583@@@5984583@@@5984583@@@5984583@@@5984583@@@5984583@@@5984583@@@5984583@@@5984583@@@5984583@@@5984583@@@5984583@@@5984583@@@5984583@@@5984583@@@5984583@@@5984583@@@5984583@@@5984583@@@5984583@@@5984583@@@5984583@@@5984583@@@5984583@@@5984583@@@5984583@@@5984583@@@5984583@@@5984583@@@5984583@@@5984583@@@5984583@@@5984583@@@5984583@@@5984583@@@5984583@@@5984583@@@5984583@@@5984583@@@5984583@@@5984583@@@5984583@@@5984583" xpos="111.75" ypos="518.25" alignment="left" rotation="0" scalex="0.5839385986328125" scaley="0.5839385986328125" filter="true"><![CDATA[French fries are the single most popular fast food in America.
In 1970, french fries surpassed regular potato sales
in the United States. In 2004, Americans ate
7.5 billion pounds of frozen french fries.]]></item>
  <item type="image" index="24" source="assets/graphics/Indicators/Indicator 13.png" xpos="112" ypos="628" width="76.7" height="78.7" rotation="-133.12042495089054"/>
  <item type="text" index="25" font="Helvetica Neue" size="28" color="5984583@@@5984583@@@5984583@@@5984583@@@5984583@@@5984583@@@5984583@@@5984583@@@5984583@@@5984583@@@5984583@@@5984583@@@5984583@@@5984583@@@5984583@@@5984583@@@5984583@@@5984583@@@5984583@@@5984583@@@5984583@@@5984583@@@5984583@@@5984583@@@5984583@@@5984583@@@5984583@@@5984583@@@5984583@@@5984583@@@5984583@@@5984583@@@5984583" xpos="212.75" ypos="679.25" alignment="right" rotation="0" scalex="0.5839385986328125" scaley="0.5839385986328125" filter="true"><![CDATA[Mcdonald's in Germany sellls beer]]></item>
  <item type="image" index="26" source="assets/graphics/Indicators/Indicator 15.png" xpos="382.75" ypos="667.25" width="76.85" height="78.85" rotation="-88.49885327536562"/>
  <item type="image" index="27" source="uploaded_image/52126669d3767.png" xpos="462.75" ypos="634.25" width="85.85" height="85.85" rotation="8.25911944271889"/>
  <item type="image" index="28" source="assets/graphics/Indicators/Indicator 8.png" xpos="138" ypos="686" width="77" height="79" rotation="0"/>
  <item type="image" index="29" source="uploaded_image/52126aebabc2e.png" xpos="465" ypos="925.75" width="116.65" height="99.8" rotation="5.2526219905142035"/>
  <item type="text" index="30" font="Helvetica Neue" size="28" color="5984583@@@5984583@@@5984583@@@5984583@@@5984583@@@5984583@@@5984583@@@5984583@@@5984583@@@5984583@@@5984583@@@5984583@@@5984583@@@5984583@@@5984583@@@5984583@@@5984583@@@5984583@@@5984583@@@5984583@@@5984583@@@5984583@@@5984583@@@5984583@@@5984583@@@5984583@@@5984583@@@5984583@@@5984583@@@5984583@@@5984583@@@5984583@@@5984583@@@5984583@@@5984583@@@5984583@@@5984583@@@5984583@@@5984583@@@5984583@@@5984583@@@5984583@@@5984583@@@5984583@@@5984583@@@5984583@@@5984583@@@5984583@@@5984583@@@5984583@@@5984583@@@5984583@@@5984583@@@5984583@@@5984583@@@5984583@@@5984583@@@5984583@@@5984583@@@5984583@@@5984583@@@5984583@@@5984583@@@5984583@@@5984583@@@5984583@@@5984583@@@5984583@@@5984583@@@5984583@@@5984583@@@5984583@@@5984583@@@5984583@@@5984583@@@5984583@@@5984583@@@5984583@@@5984583@@@5984583@@@5984583@@@5984583@@@5984583@@@5984583@@@5984583@@@5984583@@@5984583@@@5984583@@@5984583@@@5984583@@@5984583@@@5984583@@@5984583@@@5984583@@@5984583@@@5984583@@@5984583@@@5984583@@@5984583@@@5984583@@@5984583@@@5984583@@@5984583@@@5984583@@@5984583@@@5984583@@@5984583@@@5984583@@@5984583@@@5984583@@@5984583@@@5984583@@@5984583@@@5984583@@@5984583@@@5984583@@@5984583@@@5984583@@@5984583@@@5984583@@@5984583@@@5984583@@@5984583@@@5984583@@@5984583@@@5984583@@@5984583@@@5984583@@@5984583@@@5984583@@@5984583@@@5984583@@@5984583@@@5984583@@@5984583@@@5984583@@@5984583@@@5984583@@@5984583@@@5984583@@@5984583@@@5984583@@@5984583@@@5984583@@@5984583@@@5984583@@@5984583@@@5984583@@@5984583@@@5984583@@@5984583@@@5984583@@@5984583@@@5984583@@@5984583@@@5984583@@@5984583@@@5984583@@@5984583@@@5984583@@@5984583@@@5984583@@@5984583@@@5984583@@@5984583@@@5984583@@@5984583@@@5984583@@@5984583@@@5984583@@@5984583@@@5984583@@@5984583@@@5984583@@@5984583@@@5984583@@@5984583@@@5984583@@@5984583@@@5984583@@@5984583@@@5984583@@@5984583@@@5984583@@@5984583@@@5984583@@@5984583@@@5984583@@@5984583@@@5984583@@@5984583@@@5984583@@@5984583@@@5984583@@@5984583@@@5984583@@@5984583@@@5984583@@@5984583@@@5984583" xpos="179.75" ypos="768.25" alignment="left" rotation="0" scalex="0.5839385986328125" scaley="0.5839385986328125" filter="true"><![CDATA[Coca-Cola originally included coca derivatives such
as cocaine in their sodas, which at the time was not illegal.
It was originally served as a “brain tonic and
intellectual soda fountain beverage.]]></item>
  <item type="image" index="31" source="uploaded_image/521269914a343.png" xpos="51.75" ypos="705.5" width="42" height="172.65" rotation="-4.775645834592665"/>
  <item type="image" index="32" source="assets/graphics/Indicators/Indicator 7.png" xpos="358.5" ypos="915" width="76.95" height="78.95" rotation="-88.9922441375686"/>
  <item type="image" index="33" source="uploaded_image/52126dbc61e94.png" xpos="-1.25" ypos="1111.25" width="143.7" height="111.75" rotation="-10.510614029511956"/>
  <item type="text" index="34" font="Helvetica Neue" size="28" color="5984583@@@5984583@@@5984583@@@5984583@@@5984583@@@5984583@@@5984583@@@5984583@@@5984583@@@5984583@@@5984583@@@5984583@@@5984583@@@5984583@@@5984583@@@5984583@@@5984583@@@5984583@@@5984583@@@5984583@@@5984583@@@5984583@@@5984583@@@5984583@@@5984583@@@5984583@@@5984583@@@5984583@@@5984583@@@5984583@@@5984583@@@5984583@@@5984583@@@5984583@@@5984583@@@5984583@@@5984583@@@5984583@@@5984583@@@5984583@@@5984583@@@5984583@@@5984583@@@5984583@@@5984583@@@5984583@@@5984583@@@5984583@@@5984583@@@5984583@@@5984583@@@5984583@@@5984583@@@5984583@@@5984583@@@5984583@@@5984583@@@5984583@@@5984583@@@5984583@@@5984583@@@5984583@@@5984583@@@5984583@@@5984583@@@5984583@@@5984583@@@5984583@@@5984583@@@5984583@@@5984583@@@5984583@@@5984583@@@5984583@@@5984583@@@5984583@@@5984583@@@5984583@@@5984583@@@5984583@@@5984583@@@5984583@@@5984583@@@5984583@@@5984583@@@5984583@@@5984583@@@5984583@@@5984583@@@5984583@@@5984583@@@5984583@@@5984583@@@5984583@@@5984583@@@5984583@@@5984583@@@5984583@@@5984583@@@5984583@@@5984583@@@5984583@@@5984583@@@5984583@@@5984583@@@5984583@@@5984583@@@5984583@@@5984583@@@5984583@@@5984583@@@5984583@@@5984583@@@5984583@@@5984583@@@5984583@@@5984583@@@5984583@@@5984583@@@5984583@@@5984583@@@5984583@@@5984583@@@5984583@@@5984583@@@5984583@@@5984583@@@5984583@@@5984583@@@5984583@@@5984583@@@5984583@@@5984583@@@5984583@@@5984583@@@5984583@@@5984583@@@5984583@@@5984583@@@5984583@@@5984583@@@5984583@@@5984583@@@5984583@@@5984583@@@5984583@@@5984583@@@5984583@@@5984583@@@5984583@@@5984583@@@5984583@@@5984583@@@5984583@@@5984583@@@5984583@@@5984583@@@5984583@@@5984583@@@5984583@@@5984583@@@5984583@@@5984583@@@5984583@@@5984583@@@5984583@@@5984583@@@5984583@@@5984583@@@5984583@@@5984583@@@5984583@@@5984583@@@5984583@@@5984583@@@5984583@@@5984583@@@5984583@@@5984583@@@5984583@@@5984583@@@5984583@@@5984583@@@5984583@@@5984583@@@5984583@@@5984583@@@5984583@@@5984583@@@5984583@@@5984583@@@5984583@@@5984583@@@5984583@@@5984583@@@5984583@@@5984583@@@5984583@@@5984583@@@5984583@@@5984583@@@5984583@@@5984583@@@5984583@@@5984583@@@5984583@@@5984583@@@5984583@@@5984583@@@5984583@@@5984583@@@5984583@@@5984583@@@5984583@@@5984583@@@5984583@@@5984583@@@5984583@@@5984583@@@5984583@@@5984583@@@5984583@@@5984583@@@5984583@@@5984583@@@5984583@@@5984583@@@5984583@@@5984583@@@5984583@@@5984583@@@5984583@@@5984583@@@5984583" xpos="14.75" ypos="929.25" alignment="right" rotation="0" scalex="0.5839385986328125" scaley="0.5839385986328125" filter="true"><![CDATA[White Castle, started by J. Walter Anderson and
Edgar Waldo “Billy” Ingram, is considered to be the
first fast food restaurant. Its major product was a hamburger,
which had been sold as sandwiches by
street vendors since the 1890s.]]></item>
  <item type="text" index="35" font="Helvetica Neue" size="28" color="5984583@@@5984583@@@5984583@@@5984583@@@5984583@@@5984583@@@5984583@@@5984583@@@5984583@@@5984583@@@5984583@@@5984583@@@5984583@@@5984583@@@5984583@@@5984583@@@5984583@@@5984583@@@5984583@@@5984583@@@5984583@@@5984583@@@5984583@@@5984583@@@5984583@@@5984583@@@5984583@@@5984583@@@5984583@@@5984583@@@5984583@@@5984583@@@5984583@@@5984583@@@5984583@@@5984583@@@5984583@@@5984583@@@5984583@@@5984583@@@5984583@@@5984583@@@5984583@@@5984583@@@5984583@@@5984583@@@5984583@@@5984583@@@5984583@@@5984583@@@5984583@@@5984583@@@5984583@@@5984583@@@5984583@@@5984583@@@5984583@@@5984583@@@5984583@@@5984583@@@5984583@@@5984583@@@5984583@@@5984583@@@5984583@@@5984583@@@5984583@@@5984583@@@5984583@@@5984583@@@5984583@@@5984583@@@5984583@@@5984583@@@5984583@@@5984583@@@5984583@@@5984583@@@5984583@@@5984583@@@5984583@@@5984583@@@5984583@@@5984583@@@5984583@@@5984583@@@5984583@@@5984583@@@5984583@@@5984583@@@5984583@@@5984583@@@5984583@@@5984583@@@5984583@@@5984583@@@5984583@@@5984583@@@5984583@@@5984583@@@5984583@@@5984583@@@5984583@@@5984583@@@5984583@@@5984583@@@5984583@@@5984583@@@5984583@@@5984583@@@5984583@@@5984583@@@5984583@@@5984583@@@5984583@@@5984583@@@5984583@@@5984583@@@5984583@@@5984583@@@5984583@@@5984583@@@5984583@@@5984583@@@5984583@@@5984583@@@5984583@@@5984583@@@5984583@@@5984583@@@5984583@@@5984583@@@5984583@@@5984583@@@5984583@@@5984583@@@5984583@@@5984583@@@5984583@@@5984583@@@5984583@@@5984583@@@5984583@@@5984583@@@5984583@@@5984583@@@5984583@@@5984583@@@5984583@@@5984583@@@5984583@@@5984583@@@5984583@@@5984583@@@5984583@@@5984583@@@5984583@@@5984583@@@5984583@@@5984583@@@5984583@@@5984583@@@5984583@@@5984583@@@5984583@@@5984583@@@5984583@@@5984583@@@5984583@@@5984583@@@5984583@@@5984583@@@5984583@@@5984583@@@5984583@@@5984583@@@5984583@@@5984583@@@5984583@@@5984583@@@5984583@@@5984583@@@5984583@@@5984583@@@5984583@@@5984583@@@5984583@@@5984583@@@5984583@@@5984583@@@5984583@@@5984583@@@5984583@@@5984583@@@5984583@@@5984583@@@5984583@@@5984583@@@5984583@@@5984583@@@5984583@@@5984583@@@5984583@@@5984583@@@5984583@@@5984583@@@5984583@@@5984583@@@5984583@@@5984583@@@5984583@@@5984583@@@5984583@@@5984583@@@5984583@@@5984583@@@5984583@@@5984583@@@5984583@@@5984583@@@5984583@@@5984583@@@5984583@@@5984583@@@5984583@@@5984583" xpos="151.75" ypos="1103.25" alignment="left" rotation="0" scalex="0.5839385986328125" scaley="0.5839385986328125" filter="true"><![CDATA[In 1957, Burger king introduces its most famous menu item,
the Whopper. Although burger king was founded in 1954 by
James McLamore and David Edgerton, it wasn't until 1957
that the Original Whopper sandwich made it's debut. ]]></item>
  <item type="image" index="36" source="assets/graphics/Indicators/Indicator 17.png" xpos="150" ypos="1018.75" width="77" height="79" rotation="0"/>
  <item type="image" index="37" source="assets/graphics/Icons/26.png" xpos="29.25" ypos="1426.5" width="92.1" height="92.1" rotation="-7.517148698481321"/>
  <item type="text" index="38" font="Helvetica Neue" size="28" color="5984583@@@5984583@@@5984583@@@5984583@@@5984583@@@5984583@@@5984583@@@5984583@@@5984583@@@5984583@@@5984583@@@5984583@@@5984583@@@5984583@@@5984583@@@5984583@@@5984583@@@5984583@@@5984583@@@5984583@@@5984583@@@5984583@@@5984583@@@5984583@@@5984583@@@5984583@@@5984583@@@5984583@@@5984583@@@5984583@@@5984583@@@5984583@@@5984583@@@5984583@@@5984583@@@5984583@@@5984583@@@5984583@@@5984583@@@5984583@@@5984583@@@5984583@@@5984583@@@5984583@@@5984583@@@5984583@@@5984583@@@5984583@@@5984583@@@5984583@@@5984583@@@5984583@@@5984583@@@5984583@@@5984583@@@5984583@@@5984583@@@5984583@@@5984583@@@5984583@@@5984583@@@5984583@@@5984583@@@5984583@@@5984583@@@5984583@@@5984583@@@5984583@@@5984583@@@5984583@@@5984583@@@5984583@@@5984583@@@5984583@@@5984583@@@5984583@@@5984583@@@5984583@@@5984583@@@5984583@@@5984583@@@5984583@@@5984583@@@5984583@@@5984583@@@5984583@@@5984583@@@5984583@@@5984583@@@5984583@@@5984583@@@5984583@@@5984583@@@5984583@@@5984583@@@5984583@@@5984583@@@5984583" xpos="16.75" ypos="1312.25" alignment="right" rotation="0" scalex="0.5839385986328125" scaley="0.5839385986328125" filter="true"><![CDATA[Today, Coca-Cola and PepsiCo products are sold in
every country in the world, except North Korea.]]></item>
  <item type="image" index="39" source="assets/graphics/World Map/World Map 4.png" xpos="344" ypos="1253.25" width="248" height="109.5" rotation="0"/>
  <item type="image" index="40" source="assets/graphics/Indicators/Indicator 24.png" xpos="457" ypos="1172" width="77" height="79" rotation="0"/>
  <item type="image" index="41" source="assets/graphics/Indicators/Indicator 11.png" xpos="44.25" ypos="1419.25" width="77" height="79" rotation="-88.99972967084959"/>
  <item type="text" index="42" font="Helvetica Neue" size="28" color="5984583@@@5984583@@@5984583@@@5984583@@@5984583@@@5984583@@@5984583@@@5984583@@@5984583@@@5984583@@@5984583@@@5984583@@@5984583@@@5984583@@@5984583@@@5984583@@@5984583@@@5984583@@@5984583@@@5984583@@@5984583@@@5984583@@@5984583@@@5984583@@@5984583@@@5984583@@@5984583@@@5984583@@@5984583@@@5984583@@@5984583@@@5984583@@@5984583@@@5984583@@@5984583@@@5984583@@@5984583@@@5984583@@@5984583@@@5984583@@@5984583@@@5984583@@@5984583@@@5984583@@@5984583@@@5984583@@@5984583@@@5984583@@@5984583@@@5984583@@@5984583@@@5984583@@@5984583@@@5984583@@@5984583@@@5984583@@@5984583@@@5984583@@@5984583@@@5984583@@@5984583@@@5984583@@@5984583@@@5984583@@@5984583@@@5984583@@@5984583@@@5984583@@@5984583@@@5984583@@@5984583@@@5984583@@@5984583@@@5984583@@@5984583@@@5984583@@@5984583@@@5984583@@@5984583@@@5984583@@@5984583@@@5984583@@@5984583@@@5984583@@@5984583@@@5984583@@@5984583@@@5984583@@@5984583@@@5984583@@@5984583@@@5984583@@@5984583@@@5984583@@@5984583@@@5984583@@@5984583@@@5984583@@@5984583@@@5984583@@@5984583@@@5984583@@@5984583@@@5984583@@@5984583@@@5984583@@@5984583@@@5984583@@@5984583@@@5984583@@@5984583@@@5984583@@@5984583@@@5984583@@@5984583@@@5984583@@@5984583@@@5984583@@@5984583@@@5984583@@@5984583@@@5984583@@@5984583@@@5984583@@@5984583@@@5984583@@@5984583@@@5984583@@@5984583@@@5984583@@@5984583@@@5984583@@@5984583@@@5984583@@@5984583@@@5984583@@@5984583@@@5984583@@@5984583@@@5984583@@@5984583@@@5984583@@@5984583@@@5984583@@@5984583@@@5984583@@@5984583@@@5984583@@@5984583@@@5984583@@@5984583@@@5984583@@@5984583@@@5984583@@@5984583@@@5984583@@@5984583@@@5984583@@@5984583@@@5984583@@@5984583@@@5984583@@@5984583@@@5984583@@@5984583@@@5984583@@@5984583@@@5984583@@@5984583@@@5984583@@@5984583@@@5984583@@@5984583@@@5984583@@@5984583@@@5984583@@@5984583@@@5984583@@@5984583@@@5984583@@@5984583@@@5984583@@@5984583@@@5984583@@@5984583@@@5984583@@@5984583@@@5984583@@@5984583@@@5984583@@@5984583@@@5984583@@@5984583@@@5984583@@@5984583@@@5984583@@@5984583@@@5984583@@@5984583@@@5984583@@@5984583@@@5984583@@@5984583@@@5984583@@@5984583@@@5984583@@@5984583@@@5984583@@@5984583@@@5984583@@@5984583@@@5984583@@@5984583@@@5984583@@@5984583@@@5984583@@@5984583@@@5984583@@@5984583@@@5984583@@@5984583@@@5984583@@@5984583" xpos="143" ypos="1421.25" alignment="left" rotation="0" scalex="0.5698394775390625" scaley="0.5698394775390625" filter="true"><![CDATA[Television greatly expanded the ability of advertisers
to reach children and try to develop brand loyalty early in life.
Today the average American child sees more than
10,000 food advertisements each year on television.]]></item>
  <item type="text" index="43" font="Helvetica Neue" size="28" color="5984583@@@5984583@@@5984583@@@5984583@@@5984583@@@5984583@@@5984583@@@5984583@@@5984583@@@5984583@@@5984583@@@5984583@@@5984583@@@5984583@@@5984583@@@5984583@@@5984583@@@5984583@@@5984583@@@5984583@@@5984583@@@5984583@@@5984583@@@5984583@@@5984583@@@5984583@@@5984583@@@5984583@@@5984583@@@5984583@@@5984583@@@5984583@@@5984583@@@5984583@@@5984583@@@5984583@@@5984583@@@5984583@@@5984583@@@5984583@@@5984583@@@5984583@@@5984583@@@5984583@@@5984583@@@5984583@@@5984583@@@5984583@@@5984583@@@5984583@@@5984583@@@5984583@@@5984583@@@5984583@@@5984583@@@5984583@@@5984583@@@5984583@@@5984583@@@5984583@@@5984583@@@5984583@@@5984583@@@5984583@@@5984583@@@5984583@@@5984583@@@5984583@@@5984583@@@5984583@@@5984583@@@5984583@@@5984583@@@5984583@@@5984583@@@5984583@@@5984583@@@5984583@@@5984583@@@5984583@@@5984583@@@5984583@@@5984583@@@5984583@@@5984583@@@5984583@@@5984583@@@5984583@@@5984583@@@5984583@@@5984583@@@5984583@@@5984583@@@5984583@@@5984583@@@5984583@@@5984583@@@5984583@@@5984583@@@5984583@@@5984583@@@5984583@@@5984583@@@5984583@@@5984583@@@5984583@@@5984583@@@5984583@@@5984583@@@5984583@@@5984583@@@5984583@@@5984583@@@5984583@@@5984583@@@5984583@@@5984583@@@5984583@@@5984583@@@5984583@@@5984583@@@5984583@@@5984583@@@5984583@@@5984583@@@5984583@@@5984583@@@5984583@@@5984583@@@5984583@@@5984583@@@5984583@@@5984583@@@5984583@@@5984583@@@5984583@@@5984583@@@5984583@@@5984583@@@5984583@@@5984583@@@5984583@@@5984583@@@5984583@@@5984583@@@5984583@@@5984583@@@5984583@@@5984583@@@5984583@@@5984583@@@5984583@@@5984583@@@5984583@@@5984583@@@5984583@@@5984583@@@5984583@@@5984583@@@5984583@@@5984583@@@5984583@@@5984583@@@5984583@@@5984583@@@5984583@@@5984583@@@5984583@@@5984583@@@5984583@@@5984583@@@5984583@@@5984583@@@5984583@@@5984583@@@5984583@@@5984583@@@5984583@@@5984583@@@5984583@@@5984583@@@5984583@@@5984583@@@5984583@@@5984583@@@5984583@@@5984583@@@5984583@@@5984583@@@5984583@@@5984583@@@5984583@@@5984583@@@5984583@@@5984583@@@5984583@@@5984583@@@5984583@@@5984583@@@5984583@@@5984583@@@5984583@@@5984583@@@5984583@@@5984583@@@5984583@@@5984583@@@5984583@@@5984583@@@5984583@@@5984583@@@5984583@@@5984583@@@5984583@@@5984583@@@5984583@@@5984583@@@5984583@@@5984583@@@5984583@@@5984583@@@5984583@@@5984583@@@5984583@@@5984583@@@5984583@@@5984583@@@5984583@@@5984583@@@5984583@@@5984583@@@5984583@@@5984583@@@5984583@@@5984583@@@5984583@@@5984583@@@5984583@@@5984583@@@5984583@@@5984583@@@5984583@@@5984583@@@5984583@@@5984583@@@5984583@@@5984583@@@5984583@@@5984583@@@5984583@@@5984583@@@5984583@@@5984583@@@5984583@@@5984583@@@5984583@@@5984583@@@5984583@@@5984583@@@5984583@@@5984583@@@5984583@@@5984583@@@5984583@@@5984583@@@5984583@@@5984583@@@5984583@@@5984583@@@5984583@@@5984583@@@5984583@@@5984583@@@5984583@@@5984583@@@5984583@@@5984583@@@5984583@@@5984583@@@5984583@@@5984583@@@5984583@@@5984583@@@5984583@@@5984583@@@5984583@@@5984583@@@5984583@@@5984583@@@5984583@@@5984583@@@5984583@@@5984583@@@5984583@@@5984583@@@5984583@@@5984583@@@5984583@@@5984583@@@5984583@@@5984583@@@5984583@@@5984583@@@5984583@@@5984583@@@5984583@@@5984583@@@5984583@@@5984583@@@5984583@@@5984583@@@5984583@@@5984583@@@5984583" xpos="24.75" ypos="1573.25" alignment="right" rotation="0" scalex="0.5161285400390625" scaley="0.5161285400390625" filter="true"><![CDATA[Scientists have discovered that several ingredients in
fast food products have been linked to different cancers.
Some of those ingredients include; MSG, sodium nitrate,
BHA, BHT, propyl gallate, aspartame, potassiumbromate, and trans fat.
Besides the link the cancers, the most common link has been to obesity.]]></item>
  <item type="image" index="44" source="assets/graphics/Icons/10.png" xpos="462.5" ypos="1601.25" width="80.6" height="80.6" rotation="-26.551081518545775"/>
  <item type="image" index="45" source="assets/graphics/Indicators/Indicator 10.png" xpos="429" ypos="1492.25" width="77" height="79" rotation="0"/>
  <item type="text" index="46" font="Helvetica Neue" size="28" color="5984583@@@5984583@@@5984583@@@5984583@@@5984583@@@5984583@@@5984583@@@5984583@@@5984583@@@5984583@@@5984583@@@5984583@@@5984583@@@5984583@@@5984583@@@5984583@@@5984583@@@5984583@@@5984583@@@5984583@@@5984583@@@5984583@@@5984583@@@5984583@@@5984583@@@5984583@@@5984583@@@5984583@@@5984583@@@5984583@@@5984583@@@5984583@@@5984583@@@5984583@@@5984583@@@5984583@@@5984583@@@5984583@@@5984583@@@5984583@@@5984583@@@5984583@@@5984583@@@5984583@@@5984583@@@5984583@@@5984583@@@5984583@@@5984583@@@5984583@@@5984583@@@5984583@@@5984583@@@5984583@@@5984583@@@5984583@@@5984583@@@5984583@@@5984583@@@5984583@@@5984583@@@5984583@@@5984583@@@5984583@@@5984583@@@5984583@@@5984583@@@5984583@@@5984583@@@5984583@@@5984583@@@5984583@@@5984583@@@5984583@@@5984583@@@5984583@@@5984583@@@5984583@@@5984583@@@5984583@@@5984583@@@5984583@@@5984583@@@5984583@@@5984583@@@5984583@@@5984583@@@5984583@@@5984583@@@5984583@@@5984583@@@5984583@@@5984583@@@5984583@@@5984583@@@5984583@@@5984583@@@5984583@@@5984583@@@5984583@@@5984583@@@5984583@@@5984583@@@5984583@@@5984583@@@5984583@@@5984583@@@5984583@@@5984583@@@5984583@@@5984583@@@5984583@@@5984583@@@5984583@@@5984583@@@5984583@@@5984583@@@5984583@@@5984583@@@5984583@@@5984583@@@5984583@@@5984583@@@5984583@@@5984583@@@5984583@@@5984583@@@5984583@@@5984583@@@5984583@@@5984583@@@5984583@@@5984583@@@5984583@@@5984583@@@5984583@@@5984583@@@5984583@@@5984583@@@5984583@@@5984583@@@5984583@@@5984583@@@5984583@@@5984583@@@5984583@@@5984583@@@5984583@@@5984583@@@5984583@@@5984583@@@5984583@@@5984583@@@5984583@@@5984583@@@5984583@@@5984583@@@5984583@@@5984583@@@5984583@@@5984583@@@5984583@@@5984583@@@5984583@@@5984583@@@5984583@@@5984583@@@5984583@@@5984583@@@5984583@@@5984583@@@5984583@@@5984583@@@5984583@@@5984583@@@5984583@@@5984583@@@5984583@@@5984583@@@5984583@@@5984583@@@5984583@@@5984583@@@5984583@@@5984583@@@5984583@@@5984583@@@5984583@@@5984583@@@5984583@@@5984583@@@5984583@@@5984583@@@5984583@@@5984583@@@5984583@@@5984583@@@5984583@@@5984583@@@5984583@@@5984583@@@5984583@@@5984583@@@5984583@@@5984583@@@5984583@@@5984583@@@5984583@@@5984583@@@5984583@@@5984583@@@5984583@@@5984583@@@5984583@@@5984583@@@5984583@@@5984583@@@5984583@@@5984583@@@5984583@@@5984583@@@5984583@@@5984583@@@5984583@@@5984583@@@5984583@@@5984583@@@5984583@@@5984583@@@5984583@@@5984583@@@5984583@@@5984583@@@5984583@@@5984583@@@5984583@@@5984583@@@5984583@@@5984583@@@5984583@@@5984583@@@5984583@@@5984583@@@5984583@@@5984583@@@5984583@@@5984583@@@5984583@@@5984583@@@5984583@@@5984583@@@5984583@@@5984583@@@5984583@@@5984583@@@5984583@@@5984583@@@5984583@@@5984583@@@5984583@@@5984583@@@5984583@@@5984583@@@5984583@@@5984583@@@5984583@@@5984583@@@5984583@@@5984583@@@5984583@@@5984583@@@5984583@@@5984583@@@5984583@@@5984583@@@5984583@@@5984583@@@5984583@@@5984583@@@5984583@@@5984583@@@5984583@@@5984583@@@5984583@@@5984583@@@5984583@@@5984583@@@5984583@@@5984583@@@5984583@@@5984583@@@5984583@@@5984583@@@5984583@@@5984583@@@5984583@@@5984583@@@5984583@@@5984583@@@5984583@@@5984583@@@5984583@@@5984583@@@5984583@@@5984583@@@5984583@@@5984583@@@5984583@@@5984583@@@5984583@@@5984583@@@5984583@@@5984583@@@5984583@@@5984583@@@5984583@@@5984583@@@5984583@@@5984583@@@5984583@@@5984583@@@5984583@@@5984583@@@5984583@@@5984583@@@5984583@@@5984583@@@5984583@@@5984583@@@5984583@@@5984583@@@5984583@@@5984583@@@5984583@@@5984583@@@5984583@@@5984583" xpos="141.75" ypos="1732.25" alignment="left" rotation="0" scalex="0.5161285400390625" scaley="0.5161285400390625" filter="true"><![CDATA[The fast food industry has dramatically affected how cattle
and chickens are raised, slaughtered, and processed.
It also encouraged consolidation in the meatpacking industry,
such that there are now only 13 major meatpackers in America.
McDonald’s is the largest purchaser of beef and has great
influence over meatpacking practices.]]></item>
  <item type="image" index="47" source="assets/graphics/Indicators/Indicator 1.png" xpos="18" ypos="1736.75" width="77" height="79" rotation="-91.50755087151082"/>
  <item type="image" index="48" source="assets/graphics/Icons/20.png" xpos="28" ypos="1740.75" width="74" height="74" rotation="0"/>
  <item type="image" index="49" source="assets/graphics/Icons/16.png" xpos="52.25" ypos="1738.5" width="84.3" height="84.3" rotation="-5.002264982538823"/>
  <item type="image" index="50" source="assets/graphics/Indicators/Indicator 13.png" xpos="312" ypos="1829" width="77" height="79" rotation="0"/>
  <item type="text" index="51" font="Helvetica Neue" size="28" color="5984583@@@5984583@@@5984583@@@5984583@@@5984583@@@5984583@@@5984583@@@5984583@@@5984583@@@5984583@@@5984583@@@5984583@@@5984583@@@5984583@@@5984583@@@5984583@@@5984583@@@5984583@@@5984583@@@5984583@@@5984583@@@5984583@@@5984583@@@5984583@@@5984583@@@5984583@@@5984583@@@5984583@@@5984583@@@5984583@@@5984583@@@5984583@@@5984583@@@5984583@@@5984583@@@5984583@@@5984583@@@5984583@@@5984583@@@5984583@@@5984583@@@5984583@@@5984583@@@5984583@@@5984583@@@5984583@@@5984583@@@5984583@@@5984583@@@5984583@@@5984583@@@5984583@@@5984583@@@5984583@@@5984583@@@5984583@@@5984583@@@5984583@@@5984583@@@5984583@@@5984583@@@5984583@@@5984583@@@5984583@@@5984583@@@5984583@@@5984583@@@5984583@@@5984583@@@5984583@@@5984583@@@5984583@@@5984583@@@5984583@@@5984583@@@5984583@@@5984583@@@5984583@@@5984583@@@5984583@@@5984583@@@5984583@@@5984583@@@5984583@@@5984583@@@5984583@@@5984583@@@5984583@@@5984583@@@5984583@@@5984583@@@5984583@@@5984583@@@5984583@@@5984583@@@5984583@@@5984583@@@5984583@@@5984583@@@5984583@@@5984583@@@5984583@@@5984583@@@5984583@@@5984583@@@5984583@@@5984583@@@5984583@@@5984583@@@5984583@@@5984583@@@5984583@@@5984583@@@5984583@@@5984583@@@5984583@@@5984583@@@5984583@@@5984583@@@5984583@@@5984583@@@5984583@@@5984583@@@5984583@@@5984583@@@5984583@@@5984583@@@5984583@@@5984583@@@5984583@@@5984583@@@5984583@@@5984583@@@5984583@@@5984583@@@5984583@@@5984583@@@5984583@@@5984583@@@5984583@@@5984583@@@5984583@@@5984583@@@5984583@@@5984583@@@5984583@@@5984583@@@5984583@@@5984583@@@5984583" xpos="112.75" ypos="1918.25" alignment="left" rotation="0" scalex="0.5839385986328125" scaley="0.5839385986328125" filter="true"><![CDATA[When France refused to join the American-led coalition against Iraq,
some Republicans argued that the name french fries
be changed to “liberty fries]]></item>
  <item type="image" index="52" source="assets/graphics/Icons/39.png" xpos="496.4" ypos="1611.85" width="64" height="64" rotation="-8.959523814845292"/>
  <item type="image" index="53" source="assets/graphics/Icons/30.png" xpos="15" ypos="1894.5" width="94" height="94" rotation="0"/>
  <item type="text" index="54" font="Helvetica Neue" size="28" color="5984583@@@5984583@@@5984583@@@5984583@@@5984583@@@5984583@@@5984583@@@5984583@@@5984583@@@5984583@@@5984583@@@5984583@@@5984583@@@5984583@@@5984583@@@5984583@@@5984583@@@5984583@@@5984583@@@5984583@@@5984583@@@5984583@@@5984583@@@5984583@@@5984583@@@5984583@@@5984583@@@5984583@@@5984583@@@5984583@@@5984583@@@5984583@@@5984583@@@5984583@@@5984583@@@5984583@@@5984583@@@5984583@@@5984583@@@5984583@@@5984583@@@5984583@@@5984583@@@5984583@@@5984583@@@5984583@@@5984583@@@5984583@@@5984583@@@5984583@@@5984583@@@5984583@@@5984583" xpos="95.75" ypos="2063.25" alignment="right" rotation="0" scalex="0.5839385986328125" scaley="0.5839385986328125" filter="true"><![CDATA[McDonald's is the world's largest distributor of Toys]]></item>
  <item type="image" index="55" source="assets/graphics/Indicators/Indicator 7.png" xpos="302.25" ypos="2044.5" width="77" height="79" rotation="-89.24015825779408"/>
  <item type="image" index="56" source="uploaded_image/521279e0537b2.png" xpos="474" ypos="2037.25" width="96" height="96" rotation="0"/>
  <item type="image" index="57" source="assets/graphics/Indicators/Indicator 14.png" xpos="156.5" ypos="2165.75" width="77" height="78.95" rotation="-89.2496264968041"/>
  <item type="text" index="58" font="Helvetica Neue" size="28" color="5984583@@@5984583@@@5984583@@@5984583@@@5984583@@@5984583@@@5984583@@@5984583@@@5984583@@@5984583@@@5984583@@@5984583@@@5984583@@@5984583@@@5984583@@@5984583@@@5984583@@@5984583@@@5984583@@@5984583@@@5984583@@@5984583@@@5984583@@@5984583@@@5984583@@@5984583@@@5984583@@@5984583@@@5984583@@@5984583@@@5984583@@@5984583@@@5984583@@@5984583@@@5984583@@@5984583@@@5984583@@@5984583@@@5984583@@@5984583@@@5984583@@@5984583@@@5984583@@@5984583@@@5984583@@@5984583@@@5984583@@@5984583@@@5984583@@@5984583@@@5984583@@@5984583@@@5984583@@@5984583@@@5984583@@@5984583@@@5984583@@@5984583@@@5984583@@@5984583@@@5984583@@@5984583@@@5984583" xpos="170.75" ypos="2177.25" alignment="left" rotation="0" scalex="0.5839385986328125" scaley="0.5839385986328125" filter="true"><![CDATA[In ten years, there was an increase
in spending on advertising]]></item>
  <item type="image" index="59" source="assets/graphics/Indicators/Indicator 19.png" xpos="381" ypos="2286.25" width="76.95" height="78.95" rotation="-92.75601331343996"/>
  <item type="text" index="60" font="Helvetica Neue" size="28" color="5984583@@@5984583@@@5984583@@@5984583@@@5984583@@@5984583@@@5984583@@@5984583@@@5984583@@@5984583@@@5984583@@@5984583@@@5984583@@@5984583@@@5984583@@@5984583@@@5984583@@@5984583@@@5984583@@@5984583@@@5984583@@@5984583@@@5984583@@@5984583@@@5984583@@@5984583@@@5984583@@@5984583@@@5984583@@@5984583@@@5984583@@@5984583@@@5984583@@@5984583@@@5984583@@@5984583@@@5984583@@@5984583@@@5984583@@@5984583@@@5984583@@@5984583@@@5984583@@@5984583@@@5984583@@@5984583@@@5984583@@@5984583@@@5984583@@@5984583@@@5984583@@@5984583@@@5984583@@@5984583@@@5984583@@@5984583@@@5984583@@@5984583@@@5984583@@@5984583@@@5984583@@@5984583@@@5984583@@@5984583@@@5984583@@@5984583@@@5984583@@@5984583@@@5984583@@@5984583@@@5984583@@@5984583@@@5984583@@@5984583@@@5984583@@@5984583@@@5984583@@@5984583@@@5984583@@@5984583@@@5984583@@@5984583@@@5984583@@@5984583@@@5984583@@@5984583@@@5984583@@@5984583@@@5984583@@@5984583@@@5984583@@@5984583@@@5984583@@@5984583@@@5984583@@@5984583@@@5984583@@@5984583@@@5984583@@@5984583@@@5984583@@@5984583@@@5984583@@@5984583@@@5984583@@@5984583@@@5984583@@@5984583@@@5984583" xpos="77.75" ypos="2285.25" alignment="right" rotation="0" scalex="0.5839385986328125" scaley="0.5839385986328125" filter="true"><![CDATA[In 1991. there was a seven-mile-long line of cars
waiting to eat the McDonald's which first opened in Kuwait]]></item>
  <item type="image" index="61" source="uploaded_image/52127c6f9b102.png" xpos="479" ypos="2337.75" width="66.05" height="36.85" rotation="0"/>
  <item type="image" index="62" source="assets/graphics/Bar Graph/Graph 100 Percent.png" xpos="122" ypos="2157.1" width="38" height="67.3" rotation="0"/>
  <item type="image" index="63" source="assets/graphics/Bar Graph/Graph 60 Percent.png" xpos="66" ypos="2174" width="38" height="52.25" rotation="0"/>
  <item type="image" index="64" source="uploaded_image/52127c6f9b102.png" xpos="56" ypos="2338.75" width="66.05" height="36.85" rotation="0"/>
  <item type="image" index="65" source="uploaded_image/52127c6f9b102.png" xpos="132" ypos="2338.75" width="66.05" height="36.85" rotation="0"/>
  <item type="image" index="66" source="uploaded_image/52127c6f9b102.png" xpos="202" ypos="2337.75" width="66.05" height="36.85" rotation="0"/>
  <item type="image" index="67" source="uploaded_image/52127c6f9b102.png" xpos="276" ypos="2337.75" width="66.05" height="36.85" rotation="0"/>
  <item type="image" index="68" source="uploaded_image/52127c6f9b102.png" xpos="345" ypos="2337.75" width="66.05" height="36.85" rotation="0"/>
  <item type="image" index="69" source="uploaded_image/52127c6f9b102.png" xpos="413" ypos="2337.75" width="66.05" height="36.85" rotation="0"/>
  <item type="text" index="70" font="FrnkGothITC Hv BT" size="28" color="4408131@@@4408131@@@4408131@@@4408131@@@4408131@@@4408131@@@4408131@@@16777215@@@16678710@@@16678710@@@16678710@@@16678710@@@16678710@@@16678710@@@16678710@@@16678710@@@16678710@@@16678710@@@16678710@@@16777215@@@4408131@@@4408131@@@4408131@@@4408131@@@4408131@@@4408131@@@4408131@@@4408131" xpos="63" ypos="2546.25" alignment="center" rotation="0" scalex="1" scaley="1" filter="true"><![CDATA[INSTANT INFOGRAPHIC PRESENCE]]></item>
</data>